flython.py
flython-0.2.0.dist-info/LICENSE.md
flython-0.2.0.dist-info/METADATA
flython-0.2.0.dist-info/WHEEL
flython-0.2.0.dist-info/entry_points.txt
flython-0.2.0.dist-info/top_level.txt
flython-0.2.0.dist-info/RECORD
