Metadata-Version: 2.1
Name: flython
Version: 0.2.0
Summary: Static functional purity analysis for Python.
Home-page: https://github.com/brandtbucher/flython
Author: Brandt Bucher
Author-email: brandtbucher@gmail.com
License: MIT
Platform: UNKNOWN
Requires-Dist: typing ; python_version < "3.5"
